pyhelpers/__init__.py
pyhelpers/collections_utils.py
pyhelpers/hof_utils.py
pyhelpers/recursion_utils.py
pyhelpers_435-0.1.0.dist-info/METADATA
pyhelpers_435-0.1.0.dist-info/WHEEL
pyhelpers_435-0.1.0.dist-info/top_level.txt
pyhelpers_435-0.1.0.dist-info/RECORD
